auto_boost/__init__.py
auto_boost/__main__.py
auto_boost/cli.py
auto_booster-0.1.4.dist-info/licenses/LICENSE
auto_booster-0.1.4.dist-info/METADATA
auto_booster-0.1.4.dist-info/WHEEL
auto_booster-0.1.4.dist-info/entry_points.txt
auto_booster-0.1.4.dist-info/top_level.txt
auto_booster-0.1.4.dist-info/RECORD
