Metadata-Version: 2.4
Name: auto_booster
Version: 0.1.4
Summary: CLI utility for training boosting models with automated preprocessing.
Author-email: Harshad <harsh.patil317.hp@gmail.com>
Maintainer-email: Harshad <harsh.patil317.hp@gmail.com>
License: MIT License
Project-URL: Homepage, https://github.com/hpu4454/Auto_boost
Project-URL: Bug Tracker, https://github.com/hpu4454/Auto_boost/issues
Keywords: automl,gradient-boosting,kaggle,machine-learning,cli
Classifier: Development Status :: 3 - Alpha
Classifier: Intended Audience :: Science/Research
Classifier: License :: OSI Approved :: MIT License
Classifier: Programming Language :: Python :: 3
Classifier: Programming Language :: Python :: 3.8
Classifier: Programming Language :: Python :: 3.9
Classifier: Programming Language :: Python :: 3.10
Classifier: Programming Language :: Python :: 3.11
Classifier: Topic :: Scientific/Engineering :: Artificial Intelligence
Requires-Python: >=3.8
License-File: LICENSE
Requires-Dist: pandas>=1.3
Requires-Dist: numpy>=1.21
Requires-Dist: scikit-learn>=1.0
Provides-Extra: lightgbm
Requires-Dist: lightgbm>=3.3; extra == "lightgbm"
Provides-Extra: xgboost
Requires-Dist: xgboost>=1.7; extra == "xgboost"
Provides-Extra: catboost
Requires-Dist: catboost>=1.0; extra == "catboost"
Dynamic: license-file
